keen_jolt/__init__.py
keen_jolt/report.py
keen_jolt-0.1.0.dist-info/METADATA
keen_jolt-0.1.0.dist-info/WHEEL
keen_jolt-0.1.0.dist-info/top_level.txt
keen_jolt-0.1.0.dist-info/RECORD
