Metadata-Version: 2.1
Name: keen_jolt
Version: 0.1.0
Summary: Пакет для анализа финансовых транзакций
Author-email: Semyon Drozdov <s.drozdov@edu.centraluniversity.ru>
Requires-Dist: pandas
